loopctl/__init__.py
loopctl/__main__.py
loopctl-0.0.9.dist-info/METADATA
loopctl-0.0.9.dist-info/WHEEL
loopctl-0.0.9.dist-info/licenses/LICENSE
loopctl-0.0.9.dist-info/RECORD
